{
  "fireballs": [
    {
      "eventID": "Event 5415-2025",
      "eventLink": "https://fireball.amsmeteors.org/members/imo_view/event/2025/5415",
      "reportAmount": "2",
      "UTDate": "2025-08-28 21:55 UT",
      "country": "US",
      "location": "FL",
      "color": "Orange and yellow",
      "delayedSoundPositive": "",
      "delayedSoundNegative": "2",
      "concurrentSoundPositive": "",
      "concurrentSoundNegative": "2",
      "fragmentationPositive": "",
      "fragmentationNegative": "2",
      "timeSinceLastEntry": 49140
    },
    {
      "eventID": "Event 5424-2025",
      "eventLink": "https://fireball.amsmeteors.org/members/imo_view/event/2025/5424",
      "reportAmount": "3",
      "UTDate": "2025-08-29 03:39 UT",
      "country": "CH  FR",
      "location": "Bourgogne-Franche-Comté, Grand Est, Vaud",
      "color": "Vert",
      "delayedSoundPositive": "",
      "delayedSoundNegative": "2",
      "concurrentSoundPositive": "1",
      "concurrentSoundNegative": "1",
      "fragmentationPositive": "",
      "fragmentationNegative": "2",
      "timeSinceLastEntry": 20640
    },
    {
      "eventID": "Event 5423-2025",
      "eventLink": "https://fireball.amsmeteors.org/members/imo_view/event/2025/5423",
      "reportAmount": "7",
      "UTDate": "2025-08-29 03:42 UT",
      "country": "US",
      "location": "CA",
      "color": "White",
      "delayedSoundPositive": "",
      "delayedSoundNegative": "7",
      "concurrentSoundPositive": "",
      "concurrentSoundNegative": "7",
      "fragmentationPositive": "2",
      "fragmentationNegative": "2",
      "timeSinceLastEntry": 180
    }
  ]
}